MindustryTools/Collectors.py
MindustryTools/Factories.py
MindustryTools/Materials.py
MindustryTools/MindustryObject.py
MindustryTools/__init__.py
MindustryTools-0.1a1.dist-info/LICENSE
MindustryTools-0.1a1.dist-info/METADATA
MindustryTools-0.1a1.dist-info/WHEEL
MindustryTools-0.1a1.dist-info/top_level.txt
MindustryTools-0.1a1.dist-info/RECORD
